{"version":"2.0","title":"Real weighted heatmap","components":[{"type":"map","id":"map_heat","title":"Weighted intensity","height":430,"view":{"fitMode":"data"},"legend":{"defaultOpen":true},"quickFilters":[{"id":"status","label":"Status","type":"categorical","field":"category","multiSelect":true}],"layers":[{"id":"heat","name":"Asset intensity","source":{"type":"powerbi","bindings":{"latitude":"latitude","longitude":"longitude","size":"value"}},"renderer":{"type":"heatmap","weightField":"value","fieldSource":"powerbi","radius":34,"blur":24,"minOpacity":0.12,"maxIntensity":100,"gradient":{"0":"#1d4ed8","0.45":"#06b6d4","0.72":"#facc15","1":"#dc2626"},"minZoom":7,"maxZoom":18,"normalization":"viewport","interactivePoints":true},"legend":{"type":"heatIntensity","visible":true}}]}]}
